
{
  "response": {
  "version":"0.1",
  "termsofService":"http://www.wunderground.com/weather/api/d/terms.html",
  "features": {
  "history": 1
  }
	}
		,
	"history": {
		"date": {
		"pretty": "January 3, 2015",
		"year": "2015",
		"mon": "01",
		"mday": "03",
		"hour": "12",
		"min": "00",
		"tzname": "America/New_York"
		},
		"utcdate": {
		"pretty": "January 3, 2015",
		"year": "2015",
		"mon": "01",
		"mday": "03",
		"hour": "17",
		"min": "00",
		"tzname": "UTC"
		},
		"observations": [
		{
		"date": {
		"pretty": "12:51 AM EST on January 03, 2015",
		"year": "2015",
		"mon": "01",
		"mday": "03",
		"hour": "00",
		"min": "51",
		"tzname": "America/New_York"
		},
		"utcdate": {
		"pretty": "5:51 AM GMT on January 03, 2015",
		"year": "2015",
		"mon": "01",
		"mday": "03",
		"hour": "05",
		"min": "51",
		"tzname": "UTC"
		},
		"tempm":"1.7", "tempi":"35.1","dewptm":"-7.8", "dewpti":"18.0","hum":"50","wspdm":"11.1", "wspdi":"6.9","wgustm":"-9999.0", "wgusti":"-9999.0","wdird":"340","wdire":"NNW","vism":"16.1", "visi":"10.0","pressurem":"1031.5", "pressurei":"30.46","windchillm":"-1.5", "windchilli":"29.3","heatindexm":"-9999", "heatindexi":"-9999","precipm":"-9999.00", "precipi":"-9999.00","conds":"Clear","icon":"clear","fog":"0","rain":"0","snow":"0","hail":"0","thunder":"0","tornado":"0","metar":"METAR KNYC 030551Z AUTO 34006KT 10SM CLR 02/M08 A3049 RMK AO2 SLP315 T00171078 10044 20017 51016 $" },
		{
		"date": {
		"pretty": "1:51 AM EST on January 03, 2015",
		"year": "2015",
		"mon": "01",
		"mday": "03",
		"hour": "01",
		"min": "51",
		"tzname": "America/New_York"
		},
		"utcdate": {
		"pretty": "6:51 AM GMT on January 03, 2015",
		"year": "2015",
		"mon": "01",
		"mday": "03",
		"hour": "06",
		"min": "51",
		"tzname": "UTC"
		},
		"tempm":"1.1", "tempi":"34.0","dewptm":"-7.8", "dewpti":"18.0","hum":"52","wspdm":"0.0", "wspdi":"0.0","wgustm":"-9999.0", "wgusti":"-9999.0","wdird":"0","wdire":"North","vism":"16.1", "visi":"10.0","pressurem":"1031.8", "pressurei":"30.47","windchillm":"-999", "windchilli":"-999","heatindexm":"-9999", "heatindexi":"-9999","precipm":"-9999.00", "precipi":"-9999.00","conds":"Clear","icon":"clear","fog":"0","rain":"0","snow":"0","hail":"0","thunder":"0","tornado":"0","metar":"METAR KNYC 030651Z AUTO 00000KT 10SM CLR 01/M08 A3049 RMK AO2 SLP318 T00111078 $" },
		{
		"date": {
		"pretty": "2:51 AM EST on January 03, 2015",
		"year": "2015",
		"mon": "01",
		"mday": "03",
		"hour": "02",
		"min": "51",
		"tzname": "America/New_York"
		},
		"utcdate": {
		"pretty": "7:51 AM GMT on January 03, 2015",
		"year": "2015",
		"mon": "01",
		"mday": "03",
		"hour": "07",
		"min": "51",
		"tzname": "UTC"
		},
		"tempm":"1.7", "tempi":"35.1","dewptm":"-8.9", "dewpti":"16.0","hum":"46","wspdm":"9.3", "wspdi":"5.8","wgustm":"-9999.0", "wgusti":"-9999.0","wdird":"30","wdire":"NNE","vism":"16.1", "visi":"10.0","pressurem":"1032.5", "pressurei":"30.49","windchillm":"-1.1", "windchilli":"30.1","heatindexm":"-9999", "heatindexi":"-9999","precipm":"-9999.00", "precipi":"-9999.00","conds":"Clear","icon":"clear","fog":"0","rain":"0","snow":"0","hail":"0","thunder":"0","tornado":"0","metar":"METAR KNYC 030751Z AUTO 03005KT 10SM CLR 02/M09 A3051 RMK AO2 SLP325 T00171089 $" },
		{
		"date": {
		"pretty": "3:51 AM EST on January 03, 2015",
		"year": "2015",
		"mon": "01",
		"mday": "03",
		"hour": "03",
		"min": "51",
		"tzname": "America/New_York"
		},
		"utcdate": {
		"pretty": "8:51 AM GMT on January 03, 2015",
		"year": "2015",
		"mon": "01",
		"mday": "03",
		"hour": "08",
		"min": "51",
		"tzname": "UTC"
		},
		"tempm":"1.7", "tempi":"35.1","dewptm":"-8.3", "dewpti":"17.1","hum":"48","wspdm":"11.1", "wspdi":"6.9","wgustm":"-9999.0", "wgusti":"-9999.0","wdird":"70","wdire":"ENE","vism":"16.1", "visi":"10.0","pressurem":"1033.3", "pressurei":"30.52","windchillm":"-1.5", "windchilli":"29.3","heatindexm":"-9999", "heatindexi":"-9999","precipm":"-9999.00", "precipi":"-9999.00","conds":"Clear","icon":"clear","fog":"0","rain":"0","snow":"0","hail":"0","thunder":"0","tornado":"0","metar":"METAR KNYC 030851Z AUTO 07006KT 10SM CLR 02/M08 A3054 RMK AO2 SLP333 T00171083 53017 $" },
		{
		"date": {
		"pretty": "4:51 AM EST on January 03, 2015",
		"year": "2015",
		"mon": "01",
		"mday": "03",
		"hour": "04",
		"min": "51",
		"tzname": "America/New_York"
		},
		"utcdate": {
		"pretty": "9:51 AM GMT on January 03, 2015",
		"year": "2015",
		"mon": "01",
		"mday": "03",
		"hour": "09",
		"min": "51",
		"tzname": "UTC"
		},
		"tempm":"1.1", "tempi":"34.0","dewptm":"-7.8", "dewpti":"18.0","hum":"52","wspdm":"9.3", "wspdi":"5.8","wgustm":"-9999.0", "wgusti":"-9999.0","wdird":"60","wdire":"ENE","vism":"16.1", "visi":"10.0","pressurem":"1033.9", "pressurei":"30.53","windchillm":"-1.8", "windchilli":"28.8","heatindexm":"-9999", "heatindexi":"-9999","precipm":"-9999.00", "precipi":"-9999.00","conds":"Clear","icon":"clear","fog":"0","rain":"0","snow":"0","hail":"0","thunder":"0","tornado":"0","metar":"METAR KNYC 030951Z AUTO 06005KT 10SM CLR 01/M08 A3056 RMK AO2 SLP339 T00111078 $" },
		{
		"date": {
		"pretty": "5:51 AM EST on January 03, 2015",
		"year": "2015",
		"mon": "01",
		"mday": "03",
		"hour": "05",
		"min": "51",
		"tzname": "America/New_York"
		},
		"utcdate": {
		"pretty": "10:51 AM GMT on January 03, 2015",
		"year": "2015",
		"mon": "01",
		"mday": "03",
		"hour": "10",
		"min": "51",
		"tzname": "UTC"
		},
		"tempm":"1.1", "tempi":"34.0","dewptm":"-6.7", "dewpti":"19.9","hum":"56","wspdm":"9.3", "wspdi":"5.8","wgustm":"-9999.0", "wgusti":"-9999.0","wdird":"0","wdire":"Variable","vism":"16.1", "visi":"10.0","pressurem":"1034.6", "pressurei":"30.56","windchillm":"-1.8", "windchilli":"28.8","heatindexm":"-9999", "heatindexi":"-9999","precipm":"-9999.00", "precipi":"-9999.00","conds":"Clear","icon":"clear","fog":"0","rain":"0","snow":"0","hail":"0","thunder":"0","tornado":"0","metar":"METAR KNYC 031051Z AUTO VRB05KT 10SM CLR 01/M07 A3058 RMK AO2 SLP346 T00111067 $" },
		{
		"date": {
		"pretty": "6:51 AM EST on January 03, 2015",
		"year": "2015",
		"mon": "01",
		"mday": "03",
		"hour": "06",
		"min": "51",
		"tzname": "America/New_York"
		},
		"utcdate": {
		"pretty": "11:51 AM GMT on January 03, 2015",
		"year": "2015",
		"mon": "01",
		"mday": "03",
		"hour": "11",
		"min": "51",
		"tzname": "UTC"
		},
		"tempm":"1.1", "tempi":"34.0","dewptm":"-6.7", "dewpti":"19.9","hum":"56","wspdm":"9.3", "wspdi":"5.8","wgustm":"-9999.0", "wgusti":"-9999.0","wdird":"0","wdire":"Variable","vism":"16.1", "visi":"10.0","pressurem":"1034.9", "pressurei":"30.56","windchillm":"-1.8", "windchilli":"28.8","heatindexm":"-9999", "heatindexi":"-9999","precipm":"-9999.00", "precipi":"-9999.00","conds":"Clear","icon":"clear","fog":"0","rain":"0","snow":"0","hail":"0","thunder":"0","tornado":"0","metar":"METAR KNYC 031151Z AUTO VRB05KT 10SM CLR 01/M07 A3059 RMK AO2 SLP349 T00111067 10017 20006 51017 $" },
		{
		"date": {
		"pretty": "7:51 AM EST on January 03, 2015",
		"year": "2015",
		"mon": "01",
		"mday": "03",
		"hour": "07",
		"min": "51",
		"tzname": "America/New_York"
		},
		"utcdate": {
		"pretty": "12:51 PM GMT on January 03, 2015",
		"year": "2015",
		"mon": "01",
		"mday": "03",
		"hour": "12",
		"min": "51",
		"tzname": "UTC"
		},
		"tempm":"1.1", "tempi":"34.0","dewptm":"-6.7", "dewpti":"19.9","hum":"56","wspdm":"14.8", "wspdi":"9.2","wgustm":"-9999.0", "wgusti":"-9999.0","wdird":"120","wdire":"ESE","vism":"16.1", "visi":"10.0","pressurem":"1035.1", "pressurei":"30.57","windchillm":"-3.0", "windchilli":"26.6","heatindexm":"-9999", "heatindexi":"-9999","precipm":"-9999.00", "precipi":"-9999.00","conds":"Clear","icon":"clear","fog":"0","rain":"0","snow":"0","hail":"0","thunder":"0","tornado":"0","metar":"METAR KNYC 031251Z AUTO 12008KT 10SM CLR 01/M07 A3059 RMK AO2 SLP351 T00111067 $" },
		{
		"date": {
		"pretty": "8:51 AM EST on January 03, 2015",
		"year": "2015",
		"mon": "01",
		"mday": "03",
		"hour": "08",
		"min": "51",
		"tzname": "America/New_York"
		},
		"utcdate": {
		"pretty": "1:51 PM GMT on January 03, 2015",
		"year": "2015",
		"mon": "01",
		"mday": "03",
		"hour": "13",
		"min": "51",
		"tzname": "UTC"
		},
		"tempm":"1.7", "tempi":"35.1","dewptm":"-7.8", "dewpti":"18.0","hum":"50","wspdm":"11.1", "wspdi":"6.9","wgustm":"25.9", "wgusti":"16.1","wdird":"0","wdire":"Variable","vism":"16.1", "visi":"10.0","pressurem":"1035.6", "pressurei":"30.58","windchillm":"-1.5", "windchilli":"29.3","heatindexm":"-9999", "heatindexi":"-9999","precipm":"-9999.00", "precipi":"-9999.00","conds":"Clear","icon":"clear","fog":"0","rain":"0","snow":"0","hail":"0","thunder":"0","tornado":"0","metar":"METAR KNYC 031351Z AUTO VRB06G14KT 10SM CLR 02/M08 A3060 RMK AO2 SLP356 T00171078 $" },
		{
		"date": {
		"pretty": "9:51 AM EST on January 03, 2015",
		"year": "2015",
		"mon": "01",
		"mday": "03",
		"hour": "09",
		"min": "51",
		"tzname": "America/New_York"
		},
		"utcdate": {
		"pretty": "2:51 PM GMT on January 03, 2015",
		"year": "2015",
		"mon": "01",
		"mday": "03",
		"hour": "14",
		"min": "51",
		"tzname": "UTC"
		},
		"tempm":"2.2", "tempi":"36.0","dewptm":"-7.8", "dewpti":"18.0","hum":"48","wspdm":"5.6", "wspdi":"3.5","wgustm":"-9999.0", "wgusti":"-9999.0","wdird":"0","wdire":"Variable","vism":"16.1", "visi":"10.0","pressurem":"1035.7", "pressurei":"30.59","windchillm":"0.7", "windchilli":"33.3","heatindexm":"-9999", "heatindexi":"-9999","precipm":"-9999.00", "precipi":"-9999.00","conds":"Scattered Clouds","icon":"partlycloudy","fog":"0","rain":"0","snow":"0","hail":"0","thunder":"0","tornado":"0","metar":"METAR KNYC 031451Z AUTO VRB03KT 10SM SCT030 02/M08 A3061 RMK AO2 SLP357 T00221078 53008 $" },
		{
		"date": {
		"pretty": "10:15 AM EST on January 03, 2015",
		"year": "2015",
		"mon": "01",
		"mday": "03",
		"hour": "10",
		"min": "15",
		"tzname": "America/New_York"
		},
		"utcdate": {
		"pretty": "3:15 PM GMT on January 03, 2015",
		"year": "2015",
		"mon": "01",
		"mday": "03",
		"hour": "15",
		"min": "15",
		"tzname": "UTC"
		},
		"tempm":"2.8", "tempi":"37.0","dewptm":"-7.2", "dewpti":"19.0","hum":"48","wspdm":"13.0", "wspdi":"8.1","wgustm":"-9999.0", "wgusti":"-9999.0","wdird":"80","wdire":"East","vism":"16.1", "visi":"10.0","pressurem":"1035.8", "pressurei":"30.59","windchillm":"-0.6", "windchilli":"31.0","heatindexm":"-9999", "heatindexi":"-9999","precipm":"-9999.00", "precipi":"-9999.00","conds":"Mostly Cloudy","icon":"mostlycloudy","fog":"0","rain":"0","snow":"0","hail":"0","thunder":"0","tornado":"0","metar":"SPECI KNYC 031515Z AUTO 08007KT 040V110 10SM BKN029 03/M07 A3059 RMK AO2 T00281072 $" },
		{
		"date": {
		"pretty": "10:41 AM EST on January 03, 2015",
		"year": "2015",
		"mon": "01",
		"mday": "03",
		"hour": "10",
		"min": "41",
		"tzname": "America/New_York"
		},
		"utcdate": {
		"pretty": "3:41 PM GMT on January 03, 2015",
		"year": "2015",
		"mon": "01",
		"mday": "03",
		"hour": "15",
		"min": "41",
		"tzname": "UTC"
		},
		"tempm":"2.8", "tempi":"37.0","dewptm":"-7.2", "dewpti":"19.0","hum":"48","wspdm":"14.8", "wspdi":"9.2","wgustm":"-9999.0", "wgusti":"-9999.0","wdird":"110","wdire":"ESE","vism":"16.1", "visi":"10.0","pressurem":"1035.4", "pressurei":"30.58","windchillm":"-0.9", "windchilli":"30.4","heatindexm":"-9999", "heatindexi":"-9999","precipm":"-9999.00", "precipi":"-9999.00","conds":"Overcast","icon":"cloudy","fog":"0","rain":"0","snow":"0","hail":"0","thunder":"0","tornado":"0","metar":"SPECI KNYC 031541Z AUTO 11008KT 10SM SCT029 BKN080 OVC120 03/M07 A3058 RMK AO2 T00281072 $" },
		{
		"date": {
		"pretty": "10:51 AM EST on January 03, 2015",
		"year": "2015",
		"mon": "01",
		"mday": "03",
		"hour": "10",
		"min": "51",
		"tzname": "America/New_York"
		},
		"utcdate": {
		"pretty": "3:51 PM GMT on January 03, 2015",
		"year": "2015",
		"mon": "01",
		"mday": "03",
		"hour": "15",
		"min": "51",
		"tzname": "UTC"
		},
		"tempm":"2.8", "tempi":"37.0","dewptm":"-7.2", "dewpti":"19.0","hum":"48","wspdm":"13.0", "wspdi":"8.1","wgustm":"-9999.0", "wgusti":"-9999.0","wdird":"110","wdire":"ESE","vism":"16.1", "visi":"10.0","pressurem":"1034.3", "pressurei":"30.55","windchillm":"-0.6", "windchilli":"31.0","heatindexm":"-9999", "heatindexi":"-9999","precipm":"-9999.00", "precipi":"-9999.00","conds":"Overcast","icon":"cloudy","fog":"0","rain":"0","snow":"0","hail":"0","thunder":"0","tornado":"0","metar":"METAR KNYC 031551Z AUTO 11007KT 070V140 10SM BKN029 BKN080 OVC120 03/M07 A3057 RMK AO2 SLP343 T00281072 $" },
		{
		"date": {
		"pretty": "11:51 AM EST on January 03, 2015",
		"year": "2015",
		"mon": "01",
		"mday": "03",
		"hour": "11",
		"min": "51",
		"tzname": "America/New_York"
		},
		"utcdate": {
		"pretty": "4:51 PM GMT on January 03, 2015",
		"year": "2015",
		"mon": "01",
		"mday": "03",
		"hour": "16",
		"min": "51",
		"tzname": "UTC"
		},
		"tempm":"3.3", "tempi":"37.9","dewptm":"-5.6", "dewpti":"21.9","hum":"53","wspdm":"7.4", "wspdi":"4.6","wgustm":"-9999.0", "wgusti":"-9999.0","wdird":"0","wdire":"Variable","vism":"16.1", "visi":"10.0","pressurem":"1033.6", "pressurei":"30.53","windchillm":"1.3", "windchilli":"34.4","heatindexm":"-9999", "heatindexi":"-9999","precipm":"-9999.00", "precipi":"-9999.00","conds":"Overcast","icon":"cloudy","fog":"0","rain":"0","snow":"0","hail":"0","thunder":"0","tornado":"0","metar":"METAR KNYC 031651Z AUTO VRB04KT 10SM OVC028 03/M06 A3055 RMK AO2 SLP336 T00331056 $" },
		{
		"date": {
		"pretty": "12:20 PM EST on January 03, 2015",
		"year": "2015",
		"mon": "01",
		"mday": "03",
		"hour": "12",
		"min": "20",
		"tzname": "America/New_York"
		},
		"utcdate": {
		"pretty": "5:20 PM GMT on January 03, 2015",
		"year": "2015",
		"mon": "01",
		"mday": "03",
		"hour": "17",
		"min": "20",
		"tzname": "UTC"
		},
		"tempm":"3.3", "tempi":"37.9","dewptm":"-4.4", "dewpti":"24.1","hum":"57","wspdm":"14.8", "wspdi":"9.2","wgustm":"-9999.0", "wgusti":"-9999.0","wdird":"100","wdire":"East","vism":"2.8", "visi":"1.8","pressurem":"1033.7", "pressurei":"30.53","windchillm":"-0.3", "windchilli":"31.5","heatindexm":"-9999", "heatindexi":"-9999","precipm":"0.0", "precipi":"0.00","conds":"Light Snow","icon":"snow","fog":"0","rain":"0","snow":"1","hail":"0","thunder":"0","tornado":"0","metar":"SPECI KNYC 031720Z AUTO 10008KT 050V130 1 3/4SM -SN BKN027 OVC034 03/M04 A3053 RMK AO2 SNB15 P0000 T00331044 $" },
		{
		"date": {
		"pretty": "12:39 PM EST on January 03, 2015",
		"year": "2015",
		"mon": "01",
		"mday": "03",
		"hour": "12",
		"min": "39",
		"tzname": "America/New_York"
		},
		"utcdate": {
		"pretty": "5:39 PM GMT on January 03, 2015",
		"year": "2015",
		"mon": "01",
		"mday": "03",
		"hour": "17",
		"min": "39",
		"tzname": "UTC"
		},
		"tempm":"2.2", "tempi":"36.0","dewptm":"-2.2", "dewpti":"28.0","hum":"73","wspdm":"11.1", "wspdi":"6.9","wgustm":"-9999.0", "wgusti":"-9999.0","wdird":"0","wdire":"Variable","vism":"0.8", "visi":"0.5","pressurem":"1033.4", "pressurei":"30.52","windchillm":"-0.9", "windchilli":"30.3","heatindexm":"-9999", "heatindexi":"-9999","precipm":"0.3", "precipi":"0.01","conds":"Snow","icon":"snow","fog":"0","rain":"0","snow":"1","hail":"0","thunder":"0","tornado":"0","metar":"SPECI KNYC 031739Z AUTO VRB06KT 1/2SM SN SCT017 OVC026 02/M02 A3052 RMK AO2 SNB15 P0001 T00221022 $" },
		{
		"date": {
		"pretty": "12:51 PM EST on January 03, 2015",
		"year": "2015",
		"mon": "01",
		"mday": "03",
		"hour": "12",
		"min": "51",
		"tzname": "America/New_York"
		},
		"utcdate": {
		"pretty": "5:51 PM GMT on January 03, 2015",
		"year": "2015",
		"mon": "01",
		"mday": "03",
		"hour": "17",
		"min": "51",
		"tzname": "UTC"
		},
		"tempm":"1.7", "tempi":"35.1","dewptm":"-1.7", "dewpti":"28.9","hum":"78","wspdm":"13.0", "wspdi":"8.1","wgustm":"-9999.0", "wgusti":"-9999.0","wdird":"120","wdire":"ESE","vism":"3.2", "visi":"2.0","pressurem":"1032.7", "pressurei":"30.50","windchillm":"-1.9", "windchilli":"28.6","heatindexm":"-9999", "heatindexi":"-9999","precipm":"0.3", "precipi":"0.01","conds":"Light Snow","icon":"snow","fog":"0","rain":"0","snow":"1","hail":"0","thunder":"0","tornado":"0","metar":"METAR KNYC 031751Z AUTO 12007KT 2SM -SN BKN020 OVC026 02/M02 A3052 RMK AO2 SNB15 SLP327 P0001 60001 T00171017 10039 20006 55017 $" },
		{
		"date": {
		"pretty": "1:02 PM EST on January 03, 2015",
		"year": "2015",
		"mon": "01",
		"mday": "03",
		"hour": "13",
		"min": "02",
		"tzname": "America/New_York"
		},
		"utcdate": {
		"pretty": "6:02 PM GMT on January 03, 2015",
		"year": "2015",
		"mon": "01",
		"mday": "03",
		"hour": "18",
		"min": "02",
		"tzname": "UTC"
		},
		"tempm":"2.2", "tempi":"36.0","dewptm":"-1.1", "dewpti":"30.0","hum":"79","wspdm":"13.0", "wspdi":"8.1","wgustm":"-9999.0", "wgusti":"-9999.0","wdird":"80","wdire":"East","vism":"8.0", "visi":"5.0","pressurem":"1033.4", "pressurei":"30.52","windchillm":"-1.3", "windchilli":"29.6","heatindexm":"-9999", "heatindexi":"-9999","precipm":"0.0", "precipi":"0.00","conds":"Haze","icon":"hazy","fog":"0","rain":"0","snow":"0","hail":"0","thunder":"0","tornado":"0","metar":"SPECI KNYC 031802Z AUTO 08007KT 5SM HZ BKN022 OVC027 02/M01 A3052 RMK AO2 SNE01 P0000 T00221011 $" },
		{
		"date": {
		"pretty": "1:22 PM EST on January 03, 2015",
		"year": "2015",
		"mon": "01",
		"mday": "03",
		"hour": "13",
		"min": "22",
		"tzname": "America/New_York"
		},
		"utcdate": {
		"pretty": "6:22 PM GMT on January 03, 2015",
		"year": "2015",
		"mon": "01",
		"mday": "03",
		"hour": "18",
		"min": "22",
		"tzname": "UTC"
		},
		"tempm":"1.7", "tempi":"35.1","dewptm":"-1.1", "dewpti":"30.0","hum":"82","wspdm":"13.0", "wspdi":"8.1","wgustm":"-9999.0", "wgusti":"-9999.0","wdird":"60","wdire":"ENE","vism":"2.8", "visi":"1.8","pressurem":"1033.7", "pressurei":"30.53","windchillm":"-1.9", "windchilli":"28.6","heatindexm":"-9999", "heatindexi":"-9999","precipm":"0.3", "precipi":"0.01","conds":"Light Snow","icon":"snow","fog":"0","rain":"0","snow":"1","hail":"0","thunder":"0","tornado":"0","metar":"SPECI KNYC 031822Z AUTO 06007KT 1 3/4SM -SN OVC022 02/M01 A3053 RMK AO2 UPB08E13SNE01B13 P0001 T00171011 $" },
		{
		"date": {
		"pretty": "1:51 PM EST on January 03, 2015",
		"year": "2015",
		"mon": "01",
		"mday": "03",
		"hour": "13",
		"min": "51",
		"tzname": "America/New_York"
		},
		"utcdate": {
		"pretty": "6:51 PM GMT on January 03, 2015",
		"year": "2015",
		"mon": "01",
		"mday": "03",
		"hour": "18",
		"min": "51",
		"tzname": "UTC"
		},
		"tempm":"1.1", "tempi":"34.0","dewptm":"-1.1", "dewpti":"30.0","hum":"85","wspdm":"13.0", "wspdi":"8.1","wgustm":"-9999.0", "wgusti":"-9999.0","wdird":"70","wdire":"ENE","vism":"2.4", "visi":"1.5","pressurem":"1032.7", "pressurei":"30.50","windchillm":"-2.6", "windchilli":"27.2","heatindexm":"-9999", "heatindexi":"-9999","precipm":"1.0", "precipi":"0.04","conds":"Light Snow","icon":"snow","fog":"0","rain":"0","snow":"1","hail":"0","thunder":"0","tornado":"0","metar":"METAR KNYC 031851Z AUTO 07007KT 1 1/2SM -SN BR FEW009 OVC021 01/M01 A3052 RMK AO2 UPB08E13SNE01B13 SLP327 P0004 T00111011 $" },
		{
		"date": {
		"pretty": "2:11 PM EST on January 03, 2015",
		"year": "2015",
		"mon": "01",
		"mday": "03",
		"hour": "14",
		"min": "11",
		"tzname": "America/New_York"
		},
		"utcdate": {
		"pretty": "7:11 PM GMT on January 03, 2015",
		"year": "2015",
		"mon": "01",
		"mday": "03",
		"hour": "19",
		"min": "11",
		"tzname": "UTC"
		},
		"tempm":"1.1", "tempi":"34.0","dewptm":"-1.1", "dewpti":"30.0","hum":"85","wspdm":"13.0", "wspdi":"8.1","wgustm":"-9999.0", "wgusti":"-9999.0","wdird":"90","wdire":"East","vism":"1.6", "visi":"1.0","pressurem":"1032.4", "pressurei":"30.49","windchillm":"-2.6", "windchilli":"27.2","heatindexm":"-9999", "heatindexi":"-9999","precipm":"0.3", "precipi":"0.01","conds":"Light Snow","icon":"snow","fog":"0","rain":"0","snow":"1","hail":"0","thunder":"0","tornado":"0","metar":"SPECI KNYC 031911Z AUTO 09007KT 1SM -SN BR BKN007 OVC019 01/M01 A3049 RMK AO2 P0001 T00111011 $" },
		{
		"date": {
		"pretty": "2:20 PM EST on January 03, 2015",
		"year": "2015",
		"mon": "01",
		"mday": "03",
		"hour": "14",
		"min": "20",
		"tzname": "America/New_York"
		},
		"utcdate": {
		"pretty": "7:20 PM GMT on January 03, 2015",
		"year": "2015",
		"mon": "01",
		"mday": "03",
		"hour": "19",
		"min": "20",
		"tzname": "UTC"
		},
		"tempm":"1.1", "tempi":"34.0","dewptm":"-1.1", "dewpti":"30.0","hum":"85","wspdm":"9.3", "wspdi":"5.8","wgustm":"-9999.0", "wgusti":"-9999.0","wdird":"0","wdire":"Variable","vism":"1.2", "visi":"0.8","pressurem":"1032.1", "pressurei":"30.48","windchillm":"-1.8", "windchilli":"28.8","heatindexm":"-9999", "heatindexi":"-9999","precipm":"0.5", "precipi":"0.02","conds":"Light Snow","icon":"snow","fog":"0","rain":"0","snow":"1","hail":"0","thunder":"0","tornado":"0","metar":"SPECI KNYC 031920Z AUTO VRB05KT 3/4SM -SN BR BKN007 OVC019 01/M01 A3048 RMK AO2 CIG 004V010 P0002 T00111011 $" },
		{
		"date": {
		"pretty": "2:42 PM EST on January 03, 2015",
		"year": "2015",
		"mon": "01",
		"mday": "03",
		"hour": "14",
		"min": "42",
		"tzname": "America/New_York"
		},
		"utcdate": {
		"pretty": "7:42 PM GMT on January 03, 2015",
		"year": "2015",
		"mon": "01",
		"mday": "03",
		"hour": "19",
		"min": "42",
		"tzname": "UTC"
		},
		"tempm":"1.1", "tempi":"34.0","dewptm":"-0.6", "dewpti":"30.9","hum":"89","wspdm":"11.1", "wspdi":"6.9","wgustm":"-9999.0", "wgusti":"-9999.0","wdird":"0","wdire":"Variable","vism":"1.6", "visi":"1.0","pressurem":"1032.1", "pressurei":"30.48","windchillm":"-2.2", "windchilli":"28.0","heatindexm":"-9999", "heatindexi":"-9999","precipm":"1.3", "precipi":"0.05","conds":"Light Snow","icon":"snow","fog":"0","rain":"0","snow":"1","hail":"0","thunder":"0","tornado":"0","metar":"SPECI KNYC 031942Z AUTO VRB06KT 1SM -SN BR OVC004 01/M01 A3048 RMK AO2 P0005 T00111006 $" },
		{
		"date": {
		"pretty": "2:51 PM EST on January 03, 2015",
		"year": "2015",
		"mon": "01",
		"mday": "03",
		"hour": "14",
		"min": "51",
		"tzname": "America/New_York"
		},
		"utcdate": {
		"pretty": "7:51 PM GMT on January 03, 2015",
		"year": "2015",
		"mon": "01",
		"mday": "03",
		"hour": "19",
		"min": "51",
		"tzname": "UTC"
		},
		"tempm":"1.1", "tempi":"34.0","dewptm":"-0.6", "dewpti":"30.9","hum":"89","wspdm":"9.3", "wspdi":"5.8","wgustm":"-9999.0", "wgusti":"-9999.0","wdird":"60","wdire":"ENE","vism":"2.8", "visi":"1.8","pressurem":"1031.2", "pressurei":"30.45","windchillm":"-1.8", "windchilli":"28.8","heatindexm":"-9999", "heatindexi":"-9999","precipm":"1.3", "precipi":"0.05","conds":"Rain","icon":"rain","fog":"0","rain":"1","snow":"0","hail":"0","thunder":"0","tornado":"0","metar":"METAR KNYC 031951Z AUTO 06005KT 1 3/4SM RA BR OVC004 01/M01 A3047 RMK AO2 RAB51SNE51 SLP312 P0005 T00111006 $" },
		{
		"date": {
		"pretty": "3:16 PM EST on January 03, 2015",
		"year": "2015",
		"mon": "01",
		"mday": "03",
		"hour": "15",
		"min": "16",
		"tzname": "America/New_York"
		},
		"utcdate": {
		"pretty": "8:16 PM GMT on January 03, 2015",
		"year": "2015",
		"mon": "01",
		"mday": "03",
		"hour": "20",
		"min": "16",
		"tzname": "UTC"
		},
		"tempm":"1.1", "tempi":"34.0","dewptm":"-0.6", "dewpti":"30.9","hum":"89","wspdm":"7.4", "wspdi":"4.6","wgustm":"-9999.0", "wgusti":"-9999.0","wdird":"90","wdire":"East","vism":"2.8", "visi":"1.8","pressurem":"1032.1", "pressurei":"30.48","windchillm":"-1.2", "windchilli":"29.8","heatindexm":"-9999", "heatindexi":"-9999","precipm":"1.0", "precipi":"0.04","conds":"Light Rain","icon":"rain","fog":"0","rain":"1","snow":"0","hail":"0","thunder":"0","tornado":"0","metar":"SPECI KNYC 032016Z AUTO 09004KT 1 3/4SM -RA BR OVC005 01/M01 A3048 RMK AO2 P0004 T00111006 $" },
		{
		"date": {
		"pretty": "3:23 PM EST on January 03, 2015",
		"year": "2015",
		"mon": "01",
		"mday": "03",
		"hour": "15",
		"min": "23",
		"tzname": "America/New_York"
		},
		"utcdate": {
		"pretty": "8:23 PM GMT on January 03, 2015",
		"year": "2015",
		"mon": "01",
		"mday": "03",
		"hour": "20",
		"min": "23",
		"tzname": "UTC"
		},
		"tempm":"1.7", "tempi":"35.1","dewptm":"-0.6", "dewpti":"30.9","hum":"85","wspdm":"7.4", "wspdi":"4.6","wgustm":"-9999.0", "wgusti":"-9999.0","wdird":"0","wdire":"Variable","vism":"3.2", "visi":"2.0","pressurem":"1032.1", "pressurei":"30.48","windchillm":"-0.5", "windchilli":"31.0","heatindexm":"-9999", "heatindexi":"-9999","precipm":"1.3", "precipi":"0.05","conds":"Light Rain","icon":"rain","fog":"0","rain":"1","snow":"0","hail":"0","thunder":"0","tornado":"0","metar":"SPECI KNYC 032023Z AUTO VRB04KT 2SM -RA BR OVC005 02/M01 A3048 RMK AO2 P0005 T00171006 $" },
		{
		"date": {
		"pretty": "3:36 PM EST on January 03, 2015",
		"year": "2015",
		"mon": "01",
		"mday": "03",
		"hour": "15",
		"min": "36",
		"tzname": "America/New_York"
		},
		"utcdate": {
		"pretty": "8:36 PM GMT on January 03, 2015",
		"year": "2015",
		"mon": "01",
		"mday": "03",
		"hour": "20",
		"min": "36",
		"tzname": "UTC"
		},
		"tempm":"1.7", "tempi":"35.1","dewptm":"0.0", "dewpti":"32.0","hum":"89","wspdm":"11.1", "wspdi":"6.9","wgustm":"-9999.0", "wgusti":"-9999.0","wdird":"70","wdire":"ENE","vism":"2.8", "visi":"1.8","pressurem":"1031.7", "pressurei":"30.47","windchillm":"-1.5", "windchilli":"29.3","heatindexm":"-9999", "heatindexi":"-9999","precipm":"1.5", "precipi":"0.06","conds":"Light Rain","icon":"rain","fog":"0","rain":"1","snow":"0","hail":"0","thunder":"0","tornado":"0","metar":"SPECI KNYC 032036Z AUTO 07006KT 1 3/4SM -RA BR BKN005 OVC009 02/00 A3047 RMK AO2 P0006 T00170000 $" },
		{
		"date": {
		"pretty": "3:51 PM EST on January 03, 2015",
		"year": "2015",
		"mon": "01",
		"mday": "03",
		"hour": "15",
		"min": "51",
		"tzname": "America/New_York"
		},
		"utcdate": {
		"pretty": "8:51 PM GMT on January 03, 2015",
		"year": "2015",
		"mon": "01",
		"mday": "03",
		"hour": "20",
		"min": "51",
		"tzname": "UTC"
		},
		"tempm":"1.7", "tempi":"35.1","dewptm":"0.0", "dewpti":"32.0","hum":"89","wspdm":"11.1", "wspdi":"6.9","wgustm":"-9999.0", "wgusti":"-9999.0","wdird":"0","wdire":"Variable","vism":"2.4", "visi":"1.5","pressurem":"1031.0", "pressurei":"30.45","windchillm":"-1.5", "windchilli":"29.3","heatindexm":"-9999", "heatindexi":"-9999","precipm":"1.8", "precipi":"0.07","conds":"Light Rain","icon":"rain","fog":"0","rain":"1","snow":"0","hail":"0","thunder":"0","tornado":"0","metar":"METAR KNYC 032051Z AUTO VRB06KT 1 1/2SM -RA BR OVC005 02/00 A3047 RMK AO2 UPB42E46 SLP310 P0007 60016 T00170000 58018 $" },
		{
		"date": {
		"pretty": "4:31 PM EST on January 03, 2015",
		"year": "2015",
		"mon": "01",
		"mday": "03",
		"hour": "16",
		"min": "31",
		"tzname": "America/New_York"
		},
		"utcdate": {
		"pretty": "9:31 PM GMT on January 03, 2015",
		"year": "2015",
		"mon": "01",
		"mday": "03",
		"hour": "21",
		"min": "31",
		"tzname": "UTC"
		},
		"tempm":"1.7", "tempi":"35.1","dewptm":"0.0", "dewpti":"32.0","hum":"89","wspdm":"9.3", "wspdi":"5.8","wgustm":"-9999.0", "wgusti":"-9999.0","wdird":"80","wdire":"East","vism":"4.0", "visi":"2.5","pressurem":"1030.4", "pressurei":"30.43","windchillm":"-1.1", "windchilli":"30.1","heatindexm":"-9999", "heatindexi":"-9999","precipm":"1.0", "precipi":"0.04","conds":"Light Rain","icon":"rain","fog":"0","rain":"1","snow":"0","hail":"0","thunder":"0","tornado":"0","metar":"SPECI KNYC 032131Z AUTO 08005KT 2 1/2SM -RA BR OVC005 02/00 A3043 RMK AO2 UPB2056E10 P0004 T00170000 $" },
		{
		"date": {
		"pretty": "4:38 PM EST on January 03, 2015",
		"year": "2015",
		"mon": "01",
		"mday": "03",
		"hour": "16",
		"min": "38",
		"tzname": "America/New_York"
		},
		"utcdate": {
		"pretty": "9:38 PM GMT on January 03, 2015",
		"year": "2015",
		"mon": "01",
		"mday": "03",
		"hour": "21",
		"min": "38",
		"tzname": "UTC"
		},
		"tempm":"2.2", "tempi":"36.0","dewptm":"0.0", "dewpti":"32.0","hum":"86","wspdm":"9.3", "wspdi":"5.8","wgustm":"-9999.0", "wgusti":"-9999.0","wdird":"0","wdire":"Variable","vism":"4.8", "visi":"3.0","pressurem":"1030.4", "pressurei":"30.43","windchillm":"-0.5", "windchilli":"31.1","heatindexm":"-9999", "heatindexi":"-9999","precipm":"1.3", "precipi":"0.05","conds":"Overcast","icon":"cloudy","fog":"0","rain":"0","snow":"0","hail":"0","thunder":"0","tornado":"0","metar":"SPECI KNYC 032138Z AUTO VRB05KT 3SM UP BR OVC005 02/00 A3043 RMK AO2 RAE37UPB2056E10B37 P0005 T00220000 $" },
		{
		"date": {
		"pretty": "4:51 PM EST on January 03, 2015",
		"year": "2015",
		"mon": "01",
		"mday": "03",
		"hour": "16",
		"min": "51",
		"tzname": "America/New_York"
		},
		"utcdate": {
		"pretty": "9:51 PM GMT on January 03, 2015",
		"year": "2015",
		"mon": "01",
		"mday": "03",
		"hour": "21",
		"min": "51",
		"tzname": "UTC"
		},
		"tempm":"2.2", "tempi":"36.0","dewptm":"0.0", "dewpti":"32.0","hum":"86","wspdm":"13.0", "wspdi":"8.1","wgustm":"-9999.0", "wgusti":"-9999.0","wdird":"70","wdire":"ENE","vism":"4.8", "visi":"3.0","pressurem":"1029.4", "pressurei":"30.40","windchillm":"-1.3", "windchilli":"29.6","heatindexm":"-9999", "heatindexi":"-9999","precipm":"1.5", "precipi":"0.06","conds":"Light Rain","icon":"rain","fog":"0","rain":"1","snow":"0","hail":"0","thunder":"0","tornado":"0","metar":"METAR KNYC 032151Z AUTO 07007KT 3SM -RA BR OVC005 02/00 A3042 RMK AO2 RAE37B42UPB2056E10B37E42 SLP294 P0006 T00220000 $" },
		{
		"date": {
		"pretty": "5:04 PM EST on January 03, 2015",
		"year": "2015",
		"mon": "01",
		"mday": "03",
		"hour": "17",
		"min": "04",
		"tzname": "America/New_York"
		},
		"utcdate": {
		"pretty": "10:04 PM GMT on January 03, 2015",
		"year": "2015",
		"mon": "01",
		"mday": "03",
		"hour": "22",
		"min": "04",
		"tzname": "UTC"
		},
		"tempm":"2.2", "tempi":"36.0","dewptm":"0.6", "dewpti":"33.1","hum":"89","wspdm":"9.3", "wspdi":"5.8","wgustm":"-9999.0", "wgusti":"-9999.0","wdird":"70","wdire":"ENE","vism":"4.0", "visi":"2.5","pressurem":"1029.7", "pressurei":"30.41","windchillm":"-0.5", "windchilli":"31.1","heatindexm":"-9999", "heatindexi":"-9999","precipm":"0.3", "precipi":"0.01","conds":"Rain","icon":"rain","fog":"0","rain":"1","snow":"0","hail":"0","thunder":"0","tornado":"0","metar":"SPECI KNYC 032204Z AUTO 07005KT 2 1/2SM RA BR OVC005 02/01 A3041 RMK AO2 P0001 T00220006 $" },
		{
		"date": {
		"pretty": "5:31 PM EST on January 03, 2015",
		"year": "2015",
		"mon": "01",
		"mday": "03",
		"hour": "17",
		"min": "31",
		"tzname": "America/New_York"
		},
		"utcdate": {
		"pretty": "10:31 PM GMT on January 03, 2015",
		"year": "2015",
		"mon": "01",
		"mday": "03",
		"hour": "22",
		"min": "31",
		"tzname": "UTC"
		},
		"tempm":"2.2", "tempi":"36.0","dewptm":"0.6", "dewpti":"33.1","hum":"89","wspdm":"9.3", "wspdi":"5.8","wgustm":"-9999.0", "wgusti":"-9999.0","wdird":"80","wdire":"East","vism":"4.8", "visi":"3.0","pressurem":"1029.3", "pressurei":"30.40","windchillm":"-0.5", "windchilli":"31.1","heatindexm":"-9999", "heatindexi":"-9999","precipm":"1.8", "precipi":"0.07","conds":"Rain","icon":"rain","fog":"0","rain":"1","snow":"0","hail":"0","thunder":"0","tornado":"0","metar":"SPECI KNYC 032231Z AUTO 08005KT 3SM RA BR OVC005 02/01 A3040 RMK AO2 P0007 T00220006 $" },
		{
		"date": {
		"pretty": "5:38 PM EST on January 03, 2015",
		"year": "2015",
		"mon": "01",
		"mday": "03",
		"hour": "17",
		"min": "38",
		"tzname": "America/New_York"
		},
		"utcdate": {
		"pretty": "10:38 PM GMT on January 03, 2015",
		"year": "2015",
		"mon": "01",
		"mday": "03",
		"hour": "22",
		"min": "38",
		"tzname": "UTC"
		},
		"tempm":"2.2", "tempi":"36.0","dewptm":"0.6", "dewpti":"33.1","hum":"89","wspdm":"5.6", "wspdi":"3.5","wgustm":"-9999.0", "wgusti":"-9999.0","wdird":"80","wdire":"East","vism":"3.2", "visi":"2.0","pressurem":"1029.3", "pressurei":"30.40","windchillm":"0.7", "windchilli":"33.3","heatindexm":"-9999", "heatindexi":"-9999","precipm":"2.5", "precipi":"0.10","conds":"Rain","icon":"rain","fog":"0","rain":"1","snow":"0","hail":"0","thunder":"0","tornado":"0","metar":"SPECI KNYC 032238Z AUTO 08003KT 2SM RA BR OVC005 02/01 A3040 RMK AO2 P0010 T00220006 $" },
		{
		"date": {
		"pretty": "5:51 PM EST on January 03, 2015",
		"year": "2015",
		"mon": "01",
		"mday": "03",
		"hour": "17",
		"min": "51",
		"tzname": "America/New_York"
		},
		"utcdate": {
		"pretty": "10:51 PM GMT on January 03, 2015",
		"year": "2015",
		"mon": "01",
		"mday": "03",
		"hour": "22",
		"min": "51",
		"tzname": "UTC"
		},
		"tempm":"2.8", "tempi":"37.0","dewptm":"1.1", "dewpti":"34.0","hum":"89","wspdm":"7.4", "wspdi":"4.6","wgustm":"-9999.0", "wgusti":"-9999.0","wdird":"0","wdire":"Variable","vism":"4.8", "visi":"3.0","pressurem":"1028.6", "pressurei":"30.38","windchillm":"0.7", "windchilli":"33.3","heatindexm":"-9999", "heatindexi":"-9999","precipm":"3.0", "precipi":"0.12","conds":"Light Rain","icon":"rain","fog":"0","rain":"1","snow":"0","hail":"0","thunder":"0","tornado":"0","metar":"METAR KNYC 032251Z AUTO VRB04KT 3SM -RA BR OVC005 03/01 A3040 RMK AO2 SLP286 P0012 T00280011 $" },
		{
		"date": {
		"pretty": "6:14 PM EST on January 03, 2015",
		"year": "2015",
		"mon": "01",
		"mday": "03",
		"hour": "18",
		"min": "14",
		"tzname": "America/New_York"
		},
		"utcdate": {
		"pretty": "11:14 PM GMT on January 03, 2015",
		"year": "2015",
		"mon": "01",
		"mday": "03",
		"hour": "23",
		"min": "14",
		"tzname": "UTC"
		},
		"tempm":"2.8", "tempi":"37.0","dewptm":"1.1", "dewpti":"34.0","hum":"89","wspdm":"11.1", "wspdi":"6.9","wgustm":"-9999.0", "wgusti":"-9999.0","wdird":"60","wdire":"ENE","vism":"4.0", "visi":"2.5","pressurem":"1029.0", "pressurei":"30.39","windchillm":"-0.2", "windchilli":"31.6","heatindexm":"-9999", "heatindexi":"-9999","precipm":"0.3", "precipi":"0.01","conds":"Light Rain","icon":"rain","fog":"0","rain":"1","snow":"0","hail":"0","thunder":"0","tornado":"0","metar":"SPECI KNYC 032314Z AUTO 06006KT 2 1/2SM -RA BR OVC004 03/01 A3039 RMK AO2 P0001 T00280011 $" },
		{
		"date": {
		"pretty": "6:40 PM EST on January 03, 2015",
		"year": "2015",
		"mon": "01",
		"mday": "03",
		"hour": "18",
		"min": "40",
		"tzname": "America/New_York"
		},
		"utcdate": {
		"pretty": "11:40 PM GMT on January 03, 2015",
		"year": "2015",
		"mon": "01",
		"mday": "03",
		"hour": "23",
		"min": "40",
		"tzname": "UTC"
		},
		"tempm":"2.8", "tempi":"37.0","dewptm":"1.7", "dewpti":"35.1","hum":"93","wspdm":"7.4", "wspdi":"4.6","wgustm":"-9999.0", "wgusti":"-9999.0","wdird":"70","wdire":"ENE","vism":"4.8", "visi":"3.0","pressurem":"1028.3", "pressurei":"30.37","windchillm":"0.7", "windchilli":"33.3","heatindexm":"-9999", "heatindexi":"-9999","precipm":"1.3", "precipi":"0.05","conds":"Light Rain","icon":"rain","fog":"0","rain":"1","snow":"0","hail":"0","thunder":"0","tornado":"0","metar":"SPECI KNYC 032340Z AUTO 07004KT 3SM -RA BR OVC004 03/02 A3037 RMK AO2 UPB38E40 P0005 T00280017 $" },
		{
		"date": {
		"pretty": "6:51 PM EST on January 03, 2015",
		"year": "2015",
		"mon": "01",
		"mday": "03",
		"hour": "18",
		"min": "51",
		"tzname": "America/New_York"
		},
		"utcdate": {
		"pretty": "11:51 PM GMT on January 03, 2015",
		"year": "2015",
		"mon": "01",
		"mday": "03",
		"hour": "23",
		"min": "51",
		"tzname": "UTC"
		},
		"tempm":"2.8", "tempi":"37.0","dewptm":"1.7", "dewpti":"35.1","hum":"93","wspdm":"9.3", "wspdi":"5.8","wgustm":"-9999.0", "wgusti":"-9999.0","wdird":"0","wdire":"Variable","vism":"4.0", "visi":"2.5","pressurem":"1027.9", "pressurei":"30.36","windchillm":"0.2", "windchilli":"32.4","heatindexm":"-9999", "heatindexi":"-9999","precipm":"1.5", "precipi":"0.06","conds":"Rain","icon":"rain","fog":"0","rain":"1","snow":"0","hail":"0","thunder":"0","tornado":"0","metar":"METAR KNYC 032351Z AUTO VRB05KT 2 1/2SM RA BR OVC004 03/02 A3038 RMK AO2 UPB38E40 SLP279 P0006 60040 T00280017 10028 20011 56016 $" },
		{
		"date": {
		"pretty": "7:28 PM EST on January 03, 2015",
		"year": "2015",
		"mon": "01",
		"mday": "03",
		"hour": "19",
		"min": "28",
		"tzname": "America/New_York"
		},
		"utcdate": {
		"pretty": "12:28 AM GMT on January 04, 2015",
		"year": "2015",
		"mon": "01",
		"mday": "04",
		"hour": "00",
		"min": "28",
		"tzname": "UTC"
		},
		"tempm":"3.3", "tempi":"37.9","dewptm":"1.7", "dewpti":"35.1","hum":"89","wspdm":"9.3", "wspdi":"5.8","wgustm":"-9999.0", "wgusti":"-9999.0","wdird":"80","wdire":"East","vism":"4.8", "visi":"3.0","pressurem":"1027.3", "pressurei":"30.34","windchillm":"0.8", "windchilli":"33.5","heatindexm":"-9999", "heatindexi":"-9999","precipm":"1.8", "precipi":"0.07","conds":"Light Rain","icon":"rain","fog":"0","rain":"1","snow":"0","hail":"0","thunder":"0","tornado":"0","metar":"SPECI KNYC 040028Z AUTO 08005KT 3SM -RA BR OVC004 03/02 A3034 RMK AO2 P0007 T00330017 $" },
		{
		"date": {
		"pretty": "7:35 PM EST on January 03, 2015",
		"year": "2015",
		"mon": "01",
		"mday": "03",
		"hour": "19",
		"min": "35",
		"tzname": "America/New_York"
		},
		"utcdate": {
		"pretty": "12:35 AM GMT on January 04, 2015",
		"year": "2015",
		"mon": "01",
		"mday": "04",
		"hour": "00",
		"min": "35",
		"tzname": "UTC"
		},
		"tempm":"3.3", "tempi":"37.9","dewptm":"1.7", "dewpti":"35.1","hum":"89","wspdm":"9.3", "wspdi":"5.8","wgustm":"-9999.0", "wgusti":"-9999.0","wdird":"70","wdire":"ENE","vism":"3.2", "visi":"2.0","pressurem":"1027.0", "pressurei":"30.33","windchillm":"0.8", "windchilli":"33.5","heatindexm":"-9999", "heatindexi":"-9999","precipm":"2.0", "precipi":"0.08","conds":"Rain","icon":"rain","fog":"0","rain":"1","snow":"0","hail":"0","thunder":"0","tornado":"0","metar":"SPECI KNYC 040035Z AUTO 07005KT 2SM RA BR OVC004 03/02 A3033 RMK AO2 P0008 T00330017 $" },
		{
		"date": {
		"pretty": "7:51 PM EST on January 03, 2015",
		"year": "2015",
		"mon": "01",
		"mday": "03",
		"hour": "19",
		"min": "51",
		"tzname": "America/New_York"
		},
		"utcdate": {
		"pretty": "12:51 AM GMT on January 04, 2015",
		"year": "2015",
		"mon": "01",
		"mday": "04",
		"hour": "00",
		"min": "51",
		"tzname": "UTC"
		},
		"tempm":"3.9", "tempi":"39.0","dewptm":"2.2", "dewpti":"36.0","hum":"89","wspdm":"9.3", "wspdi":"5.8","wgustm":"-9999.0", "wgusti":"-9999.0","wdird":"0","wdire":"Variable","vism":"3.2", "visi":"2.0","pressurem":"1025.9", "pressurei":"30.30","windchillm":"1.5", "windchilli":"34.8","heatindexm":"-9999", "heatindexi":"-9999","precipm":"3.0", "precipi":"0.12","conds":"Light Rain","icon":"rain","fog":"0","rain":"1","snow":"0","hail":"0","thunder":"0","tornado":"0","metar":"METAR KNYC 040051Z AUTO VRB05KT 2SM -RA BR OVC004 04/02 A3032 RMK AO2 SLP259 P0012 T00390022 $" },
		{
		"date": {
		"pretty": "8:34 PM EST on January 03, 2015",
		"year": "2015",
		"mon": "01",
		"mday": "03",
		"hour": "20",
		"min": "34",
		"tzname": "America/New_York"
		},
		"utcdate": {
		"pretty": "1:34 AM GMT on January 04, 2015",
		"year": "2015",
		"mon": "01",
		"mday": "04",
		"hour": "01",
		"min": "34",
		"tzname": "UTC"
		},
		"tempm":"3.9", "tempi":"39.0","dewptm":"2.2", "dewpti":"36.0","hum":"89","wspdm":"11.1", "wspdi":"6.9","wgustm":"-9999.0", "wgusti":"-9999.0","wdird":"80","wdire":"East","vism":"4.8", "visi":"3.0","pressurem":"1025.3", "pressurei":"30.28","windchillm":"1.1", "windchilli":"34.0","heatindexm":"-9999", "heatindexi":"-9999","precipm":"0.3", "precipi":"0.01","conds":"Light Rain","icon":"rain","fog":"0","rain":"1","snow":"0","hail":"0","thunder":"0","tornado":"0","metar":"SPECI KNYC 040134Z AUTO 08006KT 3SM -RA BR OVC003 04/02 A3028 RMK AO2 P0001 T00390022 $" },
		{
		"date": {
		"pretty": "8:51 PM EST on January 03, 2015",
		"year": "2015",
		"mon": "01",
		"mday": "03",
		"hour": "20",
		"min": "51",
		"tzname": "America/New_York"
		},
		"utcdate": {
		"pretty": "1:51 AM GMT on January 04, 2015",
		"year": "2015",
		"mon": "01",
		"mday": "04",
		"hour": "01",
		"min": "51",
		"tzname": "UTC"
		},
		"tempm":"4.4", "tempi":"39.9","dewptm":"2.8", "dewpti":"37.0","hum":"89","wspdm":"14.8", "wspdi":"9.2","wgustm":"-9999.0", "wgusti":"-9999.0","wdird":"60","wdire":"ENE","vism":"4.0", "visi":"2.5","pressurem":"1023.8", "pressurei":"30.24","windchillm":"1.1", "windchilli":"33.9","heatindexm":"-9999", "heatindexi":"-9999","precipm":"0.8", "precipi":"0.03","conds":"Light Rain","icon":"rain","fog":"0","rain":"1","snow":"0","hail":"0","thunder":"0","tornado":"0","metar":"METAR KNYC 040151Z AUTO 06008KT 2 1/2SM -RA BR OVC003 04/03 A3026 RMK AO2 PRESFR SLP238 P0003 T00440028 $" },
		{
		"date": {
		"pretty": "8:59 PM EST on January 03, 2015",
		"year": "2015",
		"mon": "01",
		"mday": "03",
		"hour": "20",
		"min": "59",
		"tzname": "America/New_York"
		},
		"utcdate": {
		"pretty": "1:59 AM GMT on January 04, 2015",
		"year": "2015",
		"mon": "01",
		"mday": "04",
		"hour": "01",
		"min": "59",
		"tzname": "UTC"
		},
		"tempm":"4.4", "tempi":"39.9","dewptm":"2.8", "dewpti":"37.0","hum":"89","wspdm":"7.4", "wspdi":"4.6","wgustm":"-9999.0", "wgusti":"-9999.0","wdird":"70","wdire":"ENE","vism":"4.8", "visi":"3.0","pressurem":"1024.6", "pressurei":"30.26","windchillm":"2.6", "windchilli":"36.7","heatindexm":"-9999", "heatindexi":"-9999","precipm":"0.0", "precipi":"0.00","conds":"Light Rain","icon":"rain","fog":"0","rain":"1","snow":"0","hail":"0","thunder":"0","tornado":"0","metar":"SPECI KNYC 040159Z AUTO 07004KT 3SM -RA BR OVC003 04/03 A3026 RMK AO2 P0000 T00440028 $" },
		{
		"date": {
		"pretty": "9:10 PM EST on January 03, 2015",
		"year": "2015",
		"mon": "01",
		"mday": "03",
		"hour": "21",
		"min": "10",
		"tzname": "America/New_York"
		},
		"utcdate": {
		"pretty": "2:10 AM GMT on January 04, 2015",
		"year": "2015",
		"mon": "01",
		"mday": "04",
		"hour": "02",
		"min": "10",
		"tzname": "UTC"
		},
		"tempm":"4.4", "tempi":"39.9","dewptm":"2.8", "dewpti":"37.0","hum":"89","wspdm":"9.3", "wspdi":"5.8","wgustm":"-9999.0", "wgusti":"-9999.0","wdird":"70","wdire":"ENE","vism":"4.0", "visi":"2.5","pressurem":"1024.3", "pressurei":"30.25","windchillm":"2.1", "windchilli":"35.8","heatindexm":"-9999", "heatindexi":"-9999","precipm":"0.3", "precipi":"0.01","conds":"Light Rain","icon":"rain","fog":"0","rain":"1","snow":"0","hail":"0","thunder":"0","tornado":"0","metar":"SPECI KNYC 040210Z AUTO 07005KT 2 1/2SM -RA BR OVC004 04/03 A3025 RMK AO2 P0001 T00440028 $" },
		{
		"date": {
		"pretty": "9:38 PM EST on January 03, 2015",
		"year": "2015",
		"mon": "01",
		"mday": "03",
		"hour": "21",
		"min": "38",
		"tzname": "America/New_York"
		},
		"utcdate": {
		"pretty": "2:38 AM GMT on January 04, 2015",
		"year": "2015",
		"mon": "01",
		"mday": "04",
		"hour": "02",
		"min": "38",
		"tzname": "UTC"
		},
		"tempm":"4.4", "tempi":"39.9","dewptm":"2.8", "dewpti":"37.0","hum":"89","wspdm":"13.0", "wspdi":"8.1","wgustm":"-9999.0", "wgusti":"-9999.0","wdird":"70","wdire":"ENE","vism":"6.4", "visi":"4.0","pressurem":"1023.2", "pressurei":"30.22","windchillm":"1.4", "windchilli":"34.5","heatindexm":"-9999", "heatindexi":"-9999","precipm":"1.3", "precipi":"0.05","conds":"Light Rain","icon":"rain","fog":"0","rain":"1","snow":"0","hail":"0","thunder":"0","tornado":"0","metar":"SPECI KNYC 040238Z AUTO 07007KT 4SM -RA BR OVC004 04/03 A3022 RMK AO2 PRESFR P0005 T00440028 $" },
		{
		"date": {
		"pretty": "9:51 PM EST on January 03, 2015",
		"year": "2015",
		"mon": "01",
		"mday": "03",
		"hour": "21",
		"min": "51",
		"tzname": "America/New_York"
		},
		"utcdate": {
		"pretty": "2:51 AM GMT on January 04, 2015",
		"year": "2015",
		"mon": "01",
		"mday": "04",
		"hour": "02",
		"min": "51",
		"tzname": "UTC"
		},
		"tempm":"4.4", "tempi":"39.9","dewptm":"3.3", "dewpti":"37.9","hum":"93","wspdm":"13.0", "wspdi":"8.1","wgustm":"-9999.0", "wgusti":"-9999.0","wdird":"80","wdire":"East","vism":"4.8", "visi":"3.0","pressurem":"1021.9", "pressurei":"30.18","windchillm":"1.4", "windchilli":"34.5","heatindexm":"-9999", "heatindexi":"-9999","precipm":"1.5", "precipi":"0.06","conds":"Light Rain","icon":"rain","fog":"0","rain":"1","snow":"0","hail":"0","thunder":"0","tornado":"0","metar":"METAR KNYC 040251Z AUTO 08007KT 3SM -RA BR OVC004 04/03 A3020 RMK AO2 PRESFR SLP219 P0006 60021 T00440033 57059 $" },
		{
		"date": {
		"pretty": "10:14 PM EST on January 03, 2015",
		"year": "2015",
		"mon": "01",
		"mday": "03",
		"hour": "22",
		"min": "14",
		"tzname": "America/New_York"
		},
		"utcdate": {
		"pretty": "3:14 AM GMT on January 04, 2015",
		"year": "2015",
		"mon": "01",
		"mday": "04",
		"hour": "03",
		"min": "14",
		"tzname": "UTC"
		},
		"tempm":"5.0", "tempi":"41.0","dewptm":"3.3", "dewpti":"37.9","hum":"89","wspdm":"9.3", "wspdi":"5.8","wgustm":"-9999.0", "wgusti":"-9999.0","wdird":"70","wdire":"ENE","vism":"3.2", "visi":"2.0","pressurem":"1022.2", "pressurei":"30.19","windchillm":"2.8", "windchilli":"37.1","heatindexm":"-9999", "heatindexi":"-9999","precipm":"0.5", "precipi":"0.02","conds":"Light Rain","icon":"rain","fog":"0","rain":"1","snow":"0","hail":"0","thunder":"0","tornado":"0","metar":"SPECI KNYC 040314Z AUTO 07005KT 2SM -RA BR OVC004 05/03 A3019 RMK AO2 P0002 T00500033 $" },
		{
		"date": {
		"pretty": "10:51 PM EST on January 03, 2015",
		"year": "2015",
		"mon": "01",
		"mday": "03",
		"hour": "22",
		"min": "51",
		"tzname": "America/New_York"
		},
		"utcdate": {
		"pretty": "3:51 AM GMT on January 04, 2015",
		"year": "2015",
		"mon": "01",
		"mday": "04",
		"hour": "03",
		"min": "51",
		"tzname": "UTC"
		},
		"tempm":"5.0", "tempi":"41.0","dewptm":"3.3", "dewpti":"37.9","hum":"89","wspdm":"11.1", "wspdi":"6.9","wgustm":"-9999.0", "wgusti":"-9999.0","wdird":"0","wdire":"Variable","vism":"4.0", "visi":"2.5","pressurem":"1020.5", "pressurei":"30.14","windchillm":"2.5", "windchilli":"36.4","heatindexm":"-9999", "heatindexi":"-9999","precipm":"1.3", "precipi":"0.05","conds":"Overcast","icon":"cloudy","fog":"0","rain":"0","snow":"0","hail":"0","thunder":"0","tornado":"0","metar":"METAR KNYC 040351Z AUTO VRB06KT 2 1/2SM BR OVC004 05/03 A3016 RMK AO2 RAE42 SLP205 P0005 T00500033 $" },
		{
		"date": {
		"pretty": "11:08 PM EST on January 03, 2015",
		"year": "2015",
		"mon": "01",
		"mday": "03",
		"hour": "23",
		"min": "08",
		"tzname": "America/New_York"
		},
		"utcdate": {
		"pretty": "4:08 AM GMT on January 04, 2015",
		"year": "2015",
		"mon": "01",
		"mday": "04",
		"hour": "04",
		"min": "08",
		"tzname": "UTC"
		},
		"tempm":"5.0", "tempi":"41.0","dewptm":"3.3", "dewpti":"37.9","hum":"89","wspdm":"13.0", "wspdi":"8.1","wgustm":"-9999.0", "wgusti":"-9999.0","wdird":"60","wdire":"ENE","vism":"6.4", "visi":"4.0","pressurem":"1020.9", "pressurei":"30.15","windchillm":"2.1", "windchilli":"35.8","heatindexm":"-9999", "heatindexi":"-9999","precipm":"0.0", "precipi":"0.00","conds":"Overcast","icon":"cloudy","fog":"0","rain":"0","snow":"0","hail":"0","thunder":"0","tornado":"0","metar":"SPECI KNYC 040408Z AUTO 06007KT 030V090 4SM BR OVC004 05/03 A3015 RMK AO2 RAB0354E06 P0000 T00500033 $" },
		{
		"date": {
		"pretty": "11:29 PM EST on January 03, 2015",
		"year": "2015",
		"mon": "01",
		"mday": "03",
		"hour": "23",
		"min": "29",
		"tzname": "America/New_York"
		},
		"utcdate": {
		"pretty": "4:29 AM GMT on January 04, 2015",
		"year": "2015",
		"mon": "01",
		"mday": "04",
		"hour": "04",
		"min": "29",
		"tzname": "UTC"
		},
		"tempm":"5.0", "tempi":"41.0","dewptm":"3.9", "dewpti":"39.0","hum":"93","wspdm":"13.0", "wspdi":"8.1","wgustm":"-9999.0", "wgusti":"-9999.0","wdird":"70","wdire":"ENE","vism":"3.2", "visi":"2.0","pressurem":"1019.9", "pressurei":"30.12","windchillm":"2.1", "windchilli":"35.8","heatindexm":"-9999", "heatindexi":"-9999","precipm":"0.3", "precipi":"0.01","conds":"Overcast","icon":"cloudy","fog":"0","rain":"0","snow":"0","hail":"0","thunder":"0","tornado":"0","metar":"SPECI KNYC 040429Z AUTO 07007KT 2SM BR OVC004 05/04 A3012 RMK AO2 RAB0354E06 PRESFR P0001 T00500039 $" },
		{
		"date": {
		"pretty": "11:51 PM EST on January 03, 2015",
		"year": "2015",
		"mon": "01",
		"mday": "03",
		"hour": "23",
		"min": "51",
		"tzname": "America/New_York"
		},
		"utcdate": {
		"pretty": "4:51 AM GMT on January 04, 2015",
		"year": "2015",
		"mon": "01",
		"mday": "04",
		"hour": "04",
		"min": "51",
		"tzname": "UTC"
		},
		"tempm":"5.6", "tempi":"42.1","dewptm":"3.9", "dewpti":"39.0","hum":"89","wspdm":"11.1", "wspdi":"6.9","wgustm":"-9999.0", "wgusti":"-9999.0","wdird":"70","wdire":"ENE","vism":"4.8", "visi":"3.0","pressurem":"1018.7", "pressurei":"30.09","windchillm":"3.2", "windchilli":"37.7","heatindexm":"-9999", "heatindexi":"-9999","precipm":"0.5", "precipi":"0.02","conds":"Light Rain","icon":"rain","fog":"0","rain":"1","snow":"0","hail":"0","thunder":"0","tornado":"0","metar":"METAR KNYC 040451Z AUTO 07006KT 3SM -RA BR OVC004 06/04 A3011 RMK AO2 RAB0354E06B36 SLP187 P0002 T00560039 400560006 $" }
		],
		"dailysummary": [
		{ "date": {
		"pretty": "12:00 PM EST on January 03, 2015",
		"year": "2015",
		"mon": "01",
		"mday": "03",
		"hour": "12",
		"min": "00",
		"tzname": "America/New_York"
		},
		"fog":"0","rain":"1","snow":"1","snowfallm":"T", "snowfalli":"T","monthtodatesnowfallm":"T", "monthtodatesnowfalli":"T","since1julsnowfallm":"3.05", "since1julsnowfalli":"1.20","snowdepthm":"0.00", "snowdepthi":"0.00","hail":"0","thunder":"0","tornado":"0","meantempm":"3", "meantempi":"38","meandewptm":"-2", "meandewpti":"29","meanpressurem":"1030", "meanpressurei":"30.41","meanwindspdm":"10", "meanwindspdi":"6","meanwdire":"","meanwdird":"75","meanvism":"7", "meanvisi":"4","humidity":"","maxtempm":"6", "maxtempi":"42","mintempm":"1", "mintempi":"33","maxhumidity":"92","minhumidity":"44","maxdewptm":"4", "maxdewpti":"39","mindewptm":"-9", "mindewpti":"16","maxpressurem":"1036", "maxpressurei":"30.59","minpressurem":"1019", "minpressurei":"30.09","maxwspdm":"19", "maxwspdi":"12","minwspdm":"0", "minwspdi":"0","maxvism":"16", "maxvisi":"10","minvism":"1", "minvisi":"0","gdegreedays":"0","heatingdegreedays":"27","coolingdegreedays":"0","precipm":"18.03", "precipi":"0.71","precipsource":"","heatingdegreedaysnormal":"32","monthtodateheatingdegreedays":"85","monthtodateheatingdegreedaysnormal":"96","since1sepheatingdegreedays":"","since1sepheatingdegreedaysnormal":"","since1julheatingdegreedays":"1621","since1julheatingdegreedaysnormal":"1781","coolingdegreedaysnormal":"0","monthtodatecoolingdegreedays":"0","monthtodatecoolingdegreedaysnormal":"0","since1sepcoolingdegreedays":"","since1sepcoolingdegreedaysnormal":"","since1jancoolingdegreedays":"0","since1jancoolingdegreedaysnormal":"0" }
		]
	}
}
